cdftpy/__init__.py
cdftpy/cdft1d/__init__.py
cdftpy/cdft1d/_version.py
cdftpy/cdft1d/cli.py
cdftpy/cdft1d/coulomb.py
cdftpy/cdft1d/diis.py
cdftpy/cdft1d/exceptions.py
cdftpy/cdft1d/globals.py
cdftpy/cdft1d/io_utils.py
cdftpy/cdft1d/loggers.py
cdftpy/cdft1d/potential.py
cdftpy/cdft1d/rad_fft.py
cdftpy/cdft1d/rdf.py
cdftpy/cdft1d/rism.py
cdftpy/cdft1d/rsdft.py
cdftpy/cdft1d/simulation.py
cdftpy/cdft1d/solvent.py
cdftpy/cdft1d/units.py
cdftpy/cdft1d/viz.py
cdftpy/cdft1d/workflow.py
cdftpy/data/hcl.smdl
cdftpy/data/hcl_neutral.smdl
cdftpy/data/ion_data.json
cdftpy/data/ion_md_data.json
cdftpy/data/n2.smdl
cdftpy/data/s2.smdl
cdftpy/data/spce.smdl
cdftpy/examples/cdft1d/cl.dat
cdftpy/examples/cdft1d/f.dat
cdftpy/examples/cdft1d/k.dat
cdftpy/examples/cdft1d/na.dat
cdftpy-1.0.0.dist-info/LICENSE
cdftpy-1.0.0.dist-info/METADATA
cdftpy-1.0.0.dist-info/WHEEL
cdftpy-1.0.0.dist-info/entry_points.txt
cdftpy-1.0.0.dist-info/top_level.txt
cdftpy-1.0.0.dist-info/RECORD
