Metadata-Version: 2.1
Name: cdftpy
Version: 1.0.0
Summary: Classical density functional theory code
Home-page: UNKNOWN
Author: Marat Valiev and Gennady Chuev
Author-email: marat.valiev@gmail.com
License: GPL
Platform: UNKNOWN
Classifier: License :: OSI Approved :: GNU General Public License (GPL)
Classifier: Development Status :: 4 - Beta
Classifier: Environment :: Console
Classifier: Operating System :: MacOS :: MacOS X
Classifier: Operating System :: Microsoft :: Windows
Classifier: Operating System :: POSIX
Classifier: Programming Language :: Python
License-File: LICENSE
Requires-Dist: scipy (>=1.7.3)
Requires-Dist: numpy (>=1.21.5)
Requires-Dist: click (>=8.0.3)
Requires-Dist: holoviews (>=1.14.7)
Requires-Dist: panel (>=0.12.6)
Requires-Dist: prettytable (>=2.5.0)
